dart_version_manager/__init__.py
dart_version_manager/__main__.py
dart_version_manager/commands/__init__.py
dart_version_manager/commands/build_command.py
dart_version_manager/commands/major_command.py
dart_version_manager/commands/minor_command.py
dart_version_manager/commands/patch_command.py
dart_version_manager/commands/pre_release_command.py
dart_version_manager/core.py
dart_version_manager/main.py
dart_version_manager/utils.py
dart_version_manager-1.0.0.dist-info/entry_points.txt
dart_version_manager-1.0.0.dist-info/LICENSE
dart_version_manager-1.0.0.dist-info/WHEEL
dart_version_manager-1.0.0.dist-info/METADATA
dart_version_manager-1.0.0.dist-info/RECORD
