Metadata-Version: 2.1
Name: dart-version-manager
Version: 1.0.0
Summary: Dart Version Manager CLI implemented with Python and Typer.
Home-page: https://github.com/educup/dart_version_manager
License: MIT
Author: educup
Author-email: hello@educup.io
Requires-Python: >=3.8,<4.0
Classifier: License :: OSI Approved :: MIT License
Classifier: Programming Language :: Python :: 3
Classifier: Programming Language :: Python :: 3.8
Classifier: Programming Language :: Python :: 3.9
Requires-Dist: PyYAML (>=6.0,<7.0)
Requires-Dist: typer (>=0.3.2,<0.4.0)
Project-URL: Documentation, https://github.com/educup/dart_version_manager
Project-URL: Repository, https://github.com/educup/dart_version_manager
